akari/__init__.py
akari/cli.py
akari/gui.py
akari/utils.py
akari-0.6.dist-info/LICENSE
akari-0.6.dist-info/METADATA
akari-0.6.dist-info/WHEEL
akari-0.6.dist-info/entry_points.txt
akari-0.6.dist-info/top_level.txt
akari-0.6.dist-info/RECORD
