Metadata-Version: 2.1
Name: akari
Version: 0.6
Summary: Program to manage and tag your anime artwork
Home-page: https://github.com/mananapr/akari
Author: Manan Singh
Author-email: mananapr@gmail.com
License: UNKNOWN
Platform: UNKNOWN
Classifier: Programming Language :: Python :: 3
Classifier: License :: OSI Approved :: MIT License
Requires-Dist: requests
Requires-Dist: pyqt5
Requires-Dist: beautifulsoup4
